test_uikitblocks/migrations/0001_initial.py
test_uikitblocks/migrations/__init__.py
uikitblocks/__init__.py
uikitblocks/admin.py
uikitblocks/apps.py
uikitblocks/blocks.py
uikitblocks/models.py
uikitblocks/tests.py
uikitblocks/views.py
uikitblocks/templates/accordion.html
uikitblocks/templates/banner.html
uikitblocks/templates/button.html
uikitblocks/templates/container.html
uikitblocks/templates/grid.html
uikitblocks/templates/heading.html
uikitblocks/templates/image.html
uikitblocks/templates/lightbox.html
uikitblocks/templates/link.html
uikitblocks/templates/popup.html
uikitblocks/templates/slider.html
uikitblocks/templates/slideshow.html
uikitblocks/templates/switcher.html
uikitblocks/templates/uikit_css.html
uikitblocks/templates/uikit_js.html
uikitblocks/templatetags/__init__.py
uikitblocks/templatetags/uikit_assets.py
wagtail_uikitblocks-0.0.4.dist-info/LICENSE
wagtail_uikitblocks-0.0.4.dist-info/METADATA
wagtail_uikitblocks-0.0.4.dist-info/WHEEL
wagtail_uikitblocks-0.0.4.dist-info/top_level.txt
wagtail_uikitblocks-0.0.4.dist-info/RECORD
